[
  {
    "title": "HOURLY   Nexus Institutional Terminal",
    "date": "2026-04-27",
    "timestamp": 1777240919372,
    "excerpt": "**STRATEGIC SYNTHESIS:**\n\nThe **Bearish** bias from the Risk Desk Lead's simulation remains the \"Strongest Minority View\" after analyzing conflicting tactical simulations. This view is supported by:\n\n1. **Regulatory Friction**: EU's anti-dumping move...",
    "fileName": "swarm-hourly-1777240919362.html",
    "type": "briefing",
    "frequency": "hourly"
  }
]