[
  {
    "title": "HOURLY   Nexus Institutional Terminal",
    "date": "2026-05-03",
    "timestamp": 1777773724484,
    "excerpt": "**STRATEGIC SYNTHESIS: 2026-05-03**\n\n**INSTITUTIONAL CONSOLIDATION**\n\nThe current market context is characterized by high uncertainty and potential for price volatility. Our synthesis of 5-10 conflicting tactical simulations reveals a complex interpl...",
    "fileName": "swarm-hourly-1777773724475.html",
    "type": "briefing",
    "frequency": "hourly"
  }
]