[
  {
    "title": "HOURLY   Nexus Institutional Terminal",
    "date": "2026-04-29",
    "timestamp": 1777439072209,
    "excerpt": "**STRATEGIC SYNTHESIS:**\n\nAfter analyzing the conflicting tactical simulations from various agents, we have identified the \"Strongest Minority View\" as the **Flow Desk Senior**'s simulation, which highlights the importance of regulatory friction and ...",
    "fileName": "swarm-hourly-1777439072203.html",
    "type": "briefing",
    "frequency": "hourly"
  }
]