[
  {
    "title": "HOURLY   Nexus Institutional Terminal",
    "date": "2026-04-29",
    "timestamp": 1777442512535,
    "excerpt": "**STRATEGIC SYNTHESIS:**\n\nAfter analyzing the conflicting tactical simulations, we have identified the \"Strongest Minority View\" as the scenario presented by the [Alpha Strategist] with a score of 80. This view is supported by the following data:\n\n1....",
    "fileName": "swarm-hourly-1777442512527.html",
    "type": "briefing",
    "frequency": "hourly"
  }
]